UtilityLib/__init__.py
UtilityLib/__metadata__.py
UtilityLib/browser.py
UtilityLib/cloud.py
UtilityLib/office.py
UtilityLib/project.py
UtilityLib/utility.py
UtilityLib/core/__init__.py
UtilityLib/core/base.py
UtilityLib/core/cmd.py
UtilityLib/core/data.py
UtilityLib/core/db.py
UtilityLib/core/file.py
UtilityLib/core/log.py
UtilityLib/core/time.py
UtilityLib/lib/__init__.py
UtilityLib/lib/cmd.py
UtilityLib/lib/crypt.py
UtilityLib/lib/db.py
UtilityLib/lib/file.py
UtilityLib/lib/mail.py
UtilityLib/lib/obj.py
UtilityLib/lib/path.py
UtilityLib/lib/plot.py
UtilityLib/lib/schedule.py
UtilityLib/lib/step.py
UtilityLib/lib/task.py
UtilityLib/lib/time.py
UtilityLib/lib/url.py
UtilityLib/lib/web.py
UtilityLib/lib/cloud/__init__.py
UtilityLib/lib/cloud/aws.py
UtilityLib/lib/cloud/cpanel.py
UtilityLib/lib/cloud/gcp.py
utilitylib-2.21.4.dist-info/METADATA
utilitylib-2.21.4.dist-info/WHEEL
utilitylib-2.21.4.dist-info/top_level.txt
utilitylib-2.21.4.dist-info/RECORD
