Metadata-Version: 2.4
Name: UtilityLib
Version: 2.21.4
Summary: A comprehensive Python utility library for file management, data processing, and automation of repetitive tasks
Author-email: Vishal Kumar Sahu <mail@vishalkumarsahu.in>
Project-URL: Homepage, https://github.com/TheBiomics/UtilityLib
Project-URL: Issues, https://github.com/TheBiomics/UtilityLib/issues
Classifier: Operating System :: OS Independent
Classifier: Intended Audience :: Science/Research
Classifier: Programming Language :: Python :: 3.10
Classifier: Programming Language :: Python :: 3.11
Classifier: Programming Language :: Python :: 3.12
Classifier: Programming Language :: Python :: 3.13
Classifier: Programming Language :: Python :: 3.14
Requires-Python: <3.15,>=3.8
Requires-Dist: pandas
Requires-Dist: tqdm
Requires-Dist: requests
Requires-Dist: pyyaml
Requires-Dist: toml
Provides-Extra: all
Requires-Dist: xmltodict; extra == "all"
Requires-Dist: sqlalchemy; extra == "all"
Requires-Dist: psutil; extra == "all"
Requires-Dist: seaborn; extra == "all"
Requires-Dist: toml; extra == "all"
Requires-Dist: openpyxl; extra == "all"
Requires-Dist: schedule; extra == "all"
Requires-Dist: humanize; extra == "all"
Requires-Dist: cryptography; extra == "all"
